py_basic_commands/__init__.py
py_basic_commands/base.py
py_basic_commands/example_class.py
py_basic_commands/file_dir_scripts/__init__.py
py_basic_commands/file_dir_scripts/create_dirs.py
py_basic_commands/file_dir_scripts/create_file.py
py_basic_commands/file_dir_scripts/get_src_path.py
py_basic_commands/file_dir_scripts/join_path.py
py_basic_commands/file_dir_scripts/read_file.py
py_basic_commands/file_dir_scripts/remove_file_dir.py
py_basic_commands/file_dir_scripts/write_file.py
py_basic_commands/fscripts/__init__.py
py_basic_commands/fscripts/finput.py
py_basic_commands/fscripts/fprint.py
py_basic_commands/fscripts/fprint_array.py
py_basic_commands/json_scripts/__init__.py
py_basic_commands/json_scripts/create_json.py
py_basic_commands/json_scripts/read_json.py
py_basic_commands/json_scripts/write_json.py
py_basic_commands/other/__init__.py
py_basic_commands/other/basic_commands.py
py_basic_commands/other/choose_from_list.py
py_basic_commands/other/function_timer.py
py_basic_commands/other/timer.py
py_basic_commands-0.2.24.dist-info/LICENSE.md
py_basic_commands-0.2.24.dist-info/METADATA
py_basic_commands-0.2.24.dist-info/WHEEL
py_basic_commands-0.2.24.dist-info/top_level.txt
py_basic_commands-0.2.24.dist-info/RECORD
