Metadata-Version: 2.1
Name: py-basic-commands
Version: 0.2.24
Summary: Basic tools for Python
Home-page: https://github.com/RasseTheBoy/Py_Basic_Commands
Author: Rasmus Ohert
Author-email: Rasmus Ohert <rassemichael@gmail.com>
Project-URL: GitHub, https://github.com/RasseTheBoy/Py_Basic_Commands
Keywords: python,tool,help
Classifier: Development Status :: 5 - Production/Stable
Classifier: Intended Audience :: Education
Classifier: Programming Language :: Python :: 3
Classifier: Operating System :: OS Independent
Classifier: License :: OSI Approved :: MIT License
Requires-Python: >=3.7
License-File: LICENSE.md
